arductl/__init__.py
arductl/models.py
arductl/stack.py
arductl/storage.py
arductl-0.1.1.dist-info/WHEEL
arductl-0.1.1.dist-info/METADATA
arductl-0.1.1.dist-info/RECORD
